apf_ci/__init__.py
apf_ci/__main__.py
apf_ci/cli.py
apf_ci/android/__init__.py
apf_ci/android/build_prepare/__init__.py
apf_ci/android/build_prepare/builder/__init__.py
apf_ci/android/build_prepare/builder/android_build_prepare_builder.py
apf_ci/android/build_prepare/builder/certificate_builder.py
apf_ci/android/build_prepare/builder/clean_config_file_builder.py
apf_ci/android/build_prepare/builder/config_info_sync.py
apf_ci/android/build_prepare/builder/local_properties_builder.py
apf_ci/android/build_prepare/builder/multi_channel_builder.py
apf_ci/android/build_prepare/builder/update_project_info_builder.py
apf_ci/android/prepare/__init__.py
apf_ci/android/prepare/builder/__init__.py
apf_ci/android/prepare/builder/android_injections_builder.py
apf_ci/android/prepare/builder/android_prepare_builder.py
apf_ci/android/prepare/builder/generate_dependency_builder.py
apf_ci/android/prepare/model/__init__.py
apf_ci/android/prepare/model/meta_data_note.py
apf_ci/app_compare/__init__.py
apf_ci/app_compare/build/__init__.py
apf_ci/app_compare/build/apk_utils.py
apf_ci/app_compare/build/app_compare.py
apf_ci/app_compare/build/app_compare_android.py
apf_ci/app_compare/build/app_compare_ios.py
apf_ci/app_compare/build/app_compare_utils.py
apf_ci/app_compare/build/dependency_utils.py
apf_ci/app_compare/build/test_app_compare.py
apf_ci/app_component_compare/__init__.py
apf_ci/app_component_compare/build/__init__.py
apf_ci/app_component_compare/build/app_component_compare.py
apf_ci/app_component_compare/build/test_app_component_compare.py
apf_ci/app_init/__init__.py
apf_ci/app_init/app_config.py
apf_ci/app_init/app_init.py
apf_ci/app_init/app_resource.py
apf_ci/app_init/test_after_app_init.py
apf_ci/app_init/test_app_init.py
apf_ci/app_init/update_variable_json.py
apf_ci/app_init/utils/__init__.py
apf_ci/app_init/utils/appinfo_utils.py
apf_ci/app_init/utils/apps_utils.py
apf_ci/app_init/utils/build_config_utils.py
apf_ci/app_init/utils/image_utils.py
apf_ci-1.2.180.1.dist-info/METADATA
apf_ci-1.2.180.1.dist-info/WHEEL
apf_ci-1.2.180.1.dist-info/entry_points.txt
apf_ci-1.2.180.1.dist-info/top_level.txt
apf_ci-1.2.180.1.dist-info/RECORD
