Metadata-Version: 2.1
Name: apf-ci
Version: 1.2.180.1
Summary: App factory apf_ci build script
Home-page: http://reference.sdp.nd/appfactory/userguide/light/react-native/React%20Native%E6%9C%AC%E5%9C%B0%E8%B0%83%E8%AF%95%E5%B7%A5%E5%85%B7%E4%BD%BF%E7%94%A8%E8%AF%B4%E6%98%8E.html
Author: Lian Guo Qing
Author-email: 765789371@qq.com
License: ND License, Version 1.0
Classifier: Intended Audience :: Developers
Classifier: License :: OSI Approved :: Apache Software License
Classifier: Natural Language :: English
Classifier: Operating System :: MacOS :: MacOS X
Classifier: Operating System :: POSIX
Classifier: Operating System :: POSIX :: BSD
Classifier: Operating System :: POSIX :: Linux
Classifier: Operating System :: Microsoft :: Windows
Classifier: Programming Language :: Python
Classifier: Programming Language :: Python :: 3
Classifier: Programming Language :: Python :: 3.3
Classifier: Programming Language :: Python :: 3.4
Classifier: Programming Language :: Python :: 3.5
Classifier: Programming Language :: Python :: 3.6
Classifier: Programming Language :: Python :: Implementation :: CPython
Classifier: Programming Language :: Python :: Implementation :: PyPy
Requires-Dist: jsonmerge
Requires-Dist: pyDes
